Metadata-Version: 2.1
Name: bio-IGLoo
Version: 0.1.0
Summary: The toolkits to recover the IG region from LCL dataset.
Home-page: https://github.com/maojanlin/IGLoo
Download-URL: https://github.com/maojanlin/IGLoo/tarball/master
Author: Mao-Jan Lin
Author-email: mj.maojanlin@gmail.com
License: MIT
Keywords: Immunoglobulin,IG,assembly,Lymphoblastoid Cell Line,LCL
Classifier: Development Status :: 3 - Alpha
Classifier: Intended Audience :: Developers
Classifier: Topic :: Software Development :: Build Tools
Classifier: License :: OSI Approved :: MIT License
Classifier: Programming Language :: Python :: 3
Classifier: Programming Language :: Python :: 3.6
Classifier: Programming Language :: Python :: 3.7
Classifier: Programming Language :: Python :: 3.8
Classifier: Programming Language :: Python :: 3.9
License-File: LICENSE
